README.md
pyproject.toml
setup.py
mini_max_swing.egg-info/PKG-INFO
mini_max_swing.egg-info/SOURCES.txt
mini_max_swing.egg-info/dependency_links.txt
mini_max_swing.egg-info/entry_points.txt
mini_max_swing.egg-info/requires.txt
mini_max_swing.egg-info/top_level.txt
swing/__init__.py
swing/allure_report_common/__init__.py
swing/allure_report_common/get_report_message.py
swing/allure_report_common/save_report.py
swing/allure_report_common/send_report.py
swing/allure_report_common/util.py
swing/common/__init__.py
swing/common/common.py
swing/common/config_parse.py
swing/common/date_util.py
swing/common/feishu.py
swing/common/form_data_utils.py
swing/common/json_parse.py
swing/common/kafka_op.py
swing/common/log_assert.py
swing/common/logger_decorator.py
swing/common/mysql_op.py
swing/common/redis_op.py
swing/common/tos.py
swing/frametools/__init__.py
swing/frametools/core/__init__.py
swing/frametools/core/generate_file.py
swing/frametools/demo/__init__.py
swing/frametools/demo/pytest.ini
swing/http_generator/__init__.py
swing/http_generator/httpclient/__init__.py
swing/http_generator/httpclient/core.py
swing/http_generator/httpgenerator/__init__.py
swing/http_generator/httpgenerator/core/__init__.py
swing/http_generator/httpgenerator/core/apifox_to_request.py
swing/http_generator/httpgenerator/core/case_template.py
swing/http_generator/httpgenerator/core/code_template.py
swing/http_generator/httpgenerator/core/conf_template.py
swing/http_generator/httpgenerator/core/curl_to_request.py
swing/http_generator/httpgenerator/core/data_template.py
swing/http_generator/httpgenerator/core/lib_template.py
swing/http_generator/httpgenerator/plugins/__init__.py
swing/http_generator/httpgenerator/plugins/log/__init__.py
swing/http_generator/httpgenerator/plugins/log/logger.py
swing/http_generator/httpgenerator/utils/__init__.py
swing/http_generator/httpgenerator/utils/config_parse.py
swing/http_generator/httpgenerator/utils/json_parse.py
swing/http_generator/httpgenerator/utils/logger.py
swing/http_generator/httpgenerator/utils/tlb.py
swing/http_generator/httpgenerator/utils/utils.py
swing/http_generator/httpgenerator/utils/xray.py
swing/rpc_generator/__init__.py
swing/rpc_generator/conf/__init__.py
